{
  "type": "FeatureCollection",
  "features": [
    {
      "type": "Feature",
      "geometry": {
        "type": "Point",
        "coordinates": [
          -95.341341,
          29.72116
        ]
      },
      "properties": {
        "name": "Houston, Texas, USA"
      }
    },
    {
      "type": "Feature",
      "geometry": {
        "type": "Point",
        "coordinates": [
          -74.059329,
          4.651426
        ]
      },
      "properties": {
        "name": "Bogotá DC, Bogotá DC, Colombia"
      }
    }
  ]
}
